PrjCalculadora/__init__.py
PrjCalculadora/calculos.py
PrjCalculadora/core.py
PrjCalculadora/msg.py
PrjCalculadora/validacao.py
pjr_calculadora-0.0.2.dist-info/METADATA
pjr_calculadora-0.0.2.dist-info/WHEEL
pjr_calculadora-0.0.2.dist-info/top_level.txt
pjr_calculadora-0.0.2.dist-info/RECORD
