Metadata-Version: 2.1
Name: pjr-calculadora
Version: 0.0.2
Summary: Uma calculadora feita em python com funções para quem quiser usar.
Home-page: https://github.com/BarbosaXBarbosa/pjr_calculadora_pkg
Author: BarbosaXBarbosa
Author-email: asobrab123@hotmail.com
Requires-Python: >=3.8
